{
    pageComposition : {
        template : "examples.e4_navigation.templates.MainLayout",
        placeholders : {
        	"header" : {
        		template : "examples.e4_navigation.templates.HeaderLayout"
        	},
        	"header.leftPanel" : "Phone book | Home",
        	"header.rightPanel" : {
        		template : "examples.e4_navigation.templates.login.HeaderLogin",
        		module : "common:login"
        	},
        	"middle" : {
        		template : "examples.e4_navigation.templates.MiddleLayout"
        	},
        	"middle.leftPanel" : {
        		template : "examples.e4_navigation.templates.Menu"
        	},
        	"middle.rightPanel" : "<div style=\"padding: 10px\">Welcome to your phone book!</div>",
        	"footer" : "Just a footer, we might need it later"
        }
    },
    pageId : "HOME",
    url : "home",
    title : "Phone book | Home",
    animation : {
    	animateIn : "slide left",
    	animateOut : "slide left"
    }
}